aotools/__init__.py
aotools/_version.py
aotools/fouriertransform.py
aotools/interpolation.py
aotools/opticalpropagation.py
aotools/astronomy/__init__.py
aotools/astronomy/_astronomy.py
aotools/functions/__init__.py
aotools/functions/_functions.py
aotools/functions/karhunenLoeve.py
aotools/functions/pupil.py
aotools/functions/zernike.py
aotools/image_processing/__init__.py
aotools/image_processing/centroiders.py
aotools/image_processing/contrast.py
aotools/image_processing/psf.py
aotools/turbulence/__init__.py
aotools/turbulence/atmos_conversions.py
aotools/turbulence/infinitephasescreen.py
aotools/turbulence/phasescreen.py
aotools/turbulence/profile_compression.py
aotools/turbulence/slopecovariance.py
aotools/turbulence/temporal_ps.py
aotools/turbulence/turb.py
aotools/wfs/__init__.py
aotools/wfs/wfslib.py
aotools-1.0.7.dist-info/LICENSE.md
aotools-1.0.7.dist-info/METADATA
aotools-1.0.7.dist-info/WHEEL
aotools-1.0.7.dist-info/top_level.txt
aotools-1.0.7.dist-info/RECORD
