Metadata-Version: 2.1
Name: aotools
Version: 1.0.7
Summary: A set of useful functions for Adaptive Optics in Python
Home-page: https://github.com/aotools/aotools
Author-email: andrewpaulreeves@gmail.com, matthew.townson@durham.ac.uk
Classifier: Programming Language :: Python
Classifier: Programming Language :: Python :: 3
Classifier: Programming Language :: Python :: 3.6
Classifier: Programming Language :: Python :: 3.7
License-File: LICENSE.md
Requires-Dist: numpy
Requires-Dist: scipy
Requires-Dist: matplotlib
Requires-Dist: numba
